teleco_daisy/__init__.py
teleco_daisy-0.1.12.3.dist-info/licenses/LICENSE
teleco_daisy-0.1.12.3.dist-info/METADATA
teleco_daisy-0.1.12.3.dist-info/WHEEL
teleco_daisy-0.1.12.3.dist-info/top_level.txt
teleco_daisy-0.1.12.3.dist-info/RECORD
