Metadata-Version: 2.4
Name: teleco-daisy
Version: 0.1.12.3
Requires-Python: >=3.11
License-File: LICENSE
Requires-Dist: pydantic>=2
Requires-Dist: requests>=2.28
Dynamic: license-file
